{
  "$id": "https://ERJU/infra_DirTrackEdge",
  "$schema": "http://json-schema.org/draft-08/schema#",
  "definitions": {

  },
  "type": "object",
  "properties": {
    "trackEdge": {
      "type": "string",
      "description": "refers totrack edge"
    },
    "sameDir": {
      "type": "boolean",
      "description": "usage direction of the TrackEdge ;true: active in same direction as trackEdge, false: active in opposite direction"
    }
  },
  "required": ["trackEdge"],
  "additionalProperties": false
}
