{
  "$id": "https://ERJU/ss026_CorrectionFactor",
  "$schema": "http://json-schema.org/draft-08/schema#",
  "definitions": {

  },
  "type": "object",
  "properties": {
    "l_nvkrint": {
      "type": "integer",
      "minimum": 0,
      "description": "Train length step used to define the integrated correction factor Kr. This variable is part of the National Values."
    },
    "m_nvkrint": {
      "type": "integer",
      "minimum": 0,
      "description": "Integrated correction factor Kr. This is the train length dependentintegrated correction factor. M_NVKRINT(l) is valid for a train length between L_NVKRINT(l) and L_NVKRINT(l+1).M_NVKRINT is valid between 0m and L_NVKRINT(1)This variable is part of the National Values."
    }
  },
  "additionalProperties": false
}
