{
  "$id": "https://ERJU/ss026_DLMCondition",
  "$schema": "https://json-schema.org/draft/2019-09/schema",
  "type": "object",
  "description": "Defines the track conditions, specifying the distance to track condition changes, the validity length of the condition, and the type of track condition to ensure safe and efficient train movement.",
  "properties": {
    "d_trackcond": {
      "type": "integer",
      "minimum": 0,
      "description": "Track condition distance (The incremental distance to where the track conditions change. Comment : OnlyifQ_TRACKINIT=0, D_TRACKCOND and the following variables follow)"
    },
    "l_trackcond": {
      "type": "integer",
      "minimum": 0,
      "description": "Length for which the defined track condition is valid."
    },
    "m_trackcond": {
      "type": "integer",
      "minimum": 0,
      "description": "Type of track condition"
    }
  },
  "additionalProperties": false
}